ailabel/__init__.py
ailabel/__main__.py
ailabel/debugging.py
ailabel/label_prediction.py
ailabel/db/__init__.py
ailabel/db/crud.py
ailabel/db/database.py
ailabel/db/models.py
ailabel/entrypoints/__init__.py
ailabel/entrypoints/cli.py
ailabel/lib/llms.py
ailabel-0.4.2.dist-info/licenses/LICENSE
ailabel-0.4.2.dist-info/METADATA
ailabel-0.4.2.dist-info/WHEEL
ailabel-0.4.2.dist-info/entry_points.txt
ailabel-0.4.2.dist-info/top_level.txt
ailabel-0.4.2.dist-info/RECORD
