Metadata-Version: 2.4
Name: ailabel
Version: 0.4.2
Summary: A tool for creating and managing labeled datasets for AI training
Author: AILabel Contributors
License: MIT
Project-URL: Homepage, https://github.com/thornewolf/ailabel
Project-URL: Bug Tracker, https://github.com/thornewolf/ailabel/issues
Keywords: ai,machine-learning,labeling,datasets,classification
Classifier: Development Status :: 4 - Beta
Classifier: Environment :: Console
Classifier: Intended Audience :: Developers
Classifier: Intended Audience :: Science/Research
Classifier: License :: OSI Approved :: MIT License
Classifier: Programming Language :: Python :: 3
Classifier: Programming Language :: Python :: 3.13
Classifier: Topic :: Scientific/Engineering :: Artificial Intelligence
Classifier: Topic :: Utilities
Requires-Python: >=3.13
License-File: LICENSE
Requires-Dist: google-generativeai>=0.8.3
Requires-Dist: python-dotenv>=1.0.1
Requires-Dist: requests>=2.32.3
Requires-Dist: sqlmodel>=0.0.22
Requires-Dist: typer>=0.15.1
Provides-Extra: test
Requires-Dist: pytest>=8.1.1; extra == "test"
Requires-Dist: pytest-cov>=4.1.0; extra == "test"
Dynamic: license-file
